{
  "$schema": "https://ui.shadcn.com/schema/registry-item.json",
  "name": "truncate",
  "title": "Truncate",
  "description": "Cắt 1 dòng thông minh — chỉ bật tooltip khi chữ thật sự tràn.",
  "registryDependencies": [
    "tooltip"
  ],
  "files": [
    {
      "path": "registry/thiengthb/truncate.tsx",
      "content": "'use client';\r\n\r\nimport { useCallback, useEffect, useRef, useState, type ReactNode } from 'react';\r\nimport { Tooltip, TooltipContent, TooltipTrigger } from '@/components/ui/tooltip';\r\nimport { cn } from '@/lib/utils';\r\n\r\n/**\r\n * SMART single-line truncate: only shows the tooltip when the text actually overflows — no\r\n * pointless tooltip for short text. The tooltip shows the full content right below the cursor\r\n * (default side \"bottom\"). Overflow is measured via scrollWidth + ResizeObserver.\r\n */\r\nexport function Truncate({\r\n  children,\r\n  full,\r\n  className,\r\n  side = 'bottom',\r\n}: {\r\n  children: ReactNode;\r\n  /** full content shown in the tooltip; defaults to children (use when children is a string) */\r\n  full?: ReactNode;\r\n  className?: string;\r\n  side?: 'top' | 'right' | 'bottom' | 'left';\r\n}) {\r\n  const ref = useRef<HTMLSpanElement>(null);\r\n  const [overflow, setOverflow] = useState(false);\r\n\r\n  const check = useCallback(() => {\r\n    const el = ref.current;\r\n    if (el) setOverflow(el.scrollWidth > el.clientWidth + 1);\r\n  }, []);\r\n\r\n  useEffect(() => {\r\n    check();\r\n    const el = ref.current;\r\n    if (!el) return;\r\n    const ro = new ResizeObserver(check);\r\n    ro.observe(el);\r\n    return () => ro.disconnect();\r\n  }, [check, children]);\r\n\r\n  const span = (\r\n    <span ref={ref} className={cn('block min-w-0 truncate', className)}>\r\n      {children}\r\n    </span>\r\n  );\r\n\r\n  if (!overflow) return span;\r\n\r\n  return (\r\n    <Tooltip>\r\n      <TooltipTrigger asChild>{span}</TooltipTrigger>\r\n      <TooltipContent side={side} className=\"max-w-xs break-words whitespace-normal\">\r\n        {full ?? children}\r\n      </TooltipContent>\r\n    </Tooltip>\r\n  );\r\n}\r\n",
      "type": "registry:ui",
      "target": "components/ui/truncate.tsx"
    }
  ],
  "type": "registry:ui"
}